okntool/__init__.py
okntool/indi_va_table_template.html
okntool/oknserver_graph_plot_config.json
okntool/okntool.py
okntool/simpler_plot_config.json
okntool/sum_va_table_template.html
okntool-8.4.3.dist-info/licenses/LICENSE
okntool-8.4.3.dist-info/METADATA
okntool-8.4.3.dist-info/WHEEL
okntool-8.4.3.dist-info/entry_points.txt
okntool-8.4.3.dist-info/top_level.txt
okntool-8.4.3.dist-info/RECORD
