Metadata-Version: 2.4
Name: okntool
Version: 8.4.3
Summary: Command line program to carry out okn related tasks.
Author-email: Zaw Lin Tun <zawlintun1511@gmail.com>
Project-URL: Homepage, https://github.com/jtur044/okntool
Project-URL: Bug Tracker, https://github.com/jtur044/okntool/issues
Classifier: Programming Language :: Python :: 3
Classifier: License :: OSI Approved :: Apache Software License
Classifier: Operating System :: OS Independent
Requires-Python: >=3.9
License-File: LICENSE
Requires-Dist: setuptools>=61.0
Requires-Dist: opencv-python>=4.8.1.78
Requires-Dist: scipy>=1.11.3
Requires-Dist: numpy>=1.26.1
Requires-Dist: commentjson
Requires-Dist: ehdg_tools>=4.6.3
Requires-Dist: chevron
Requires-Dist: matplotlib>=3.9.2
Dynamic: license-file
